json24/__init__.py
json24/parser.py
json24-0.1.0.dist-info/METADATA
json24-0.1.0.dist-info/WHEEL
json24-0.1.0.dist-info/top_level.txt
json24-0.1.0.dist-info/RECORD
