Metadata-Version: 2.1
Name: json24
Version: 0.1.0
Summary: A library to parse partial JSON strings with optional logging for faulty JSON.
Home-page: https://github.com/yourusername/json24
Author: Your Name
Author-email: your.email@example.com
Classifier: Programming Language :: Python :: 3
Classifier: License :: OSI Approved :: MIT License
Classifier: Operating System :: OS Independent
Requires-Python: >=3.6
